wottle
