Metadata-Version: 2.1
Name: wottle
Version: 2.0.2
Summary: Asynchronous library for getting the weather forecast in the desired city.
Home-page: https://github.com/qxtony/wottle
Author: qxtony
Author-email: qxtonydev@gmail.com
License: UNKNOWN
Platform: UNKNOWN
Classifier: Programming Language :: Python :: 3.7
Classifier: License :: OSI Approved :: MIT License
Classifier: Operating System :: OS Independent
Requires-Python: >=3.7
